primestg/__init__.py
primestg/cli.py
primestg/contract_templates.py
primestg/dlms_templates.py
primestg/event_groups.py
primestg/message.py
primestg/service.py
primestg/utils.py
primestg/ziv_service.py
primestg/cycle/__init__.py
primestg/cycle/cycles.py
primestg/order/__init__.py
primestg/order/base.py
primestg/order/orders.py
primestg/report/__init__.py
primestg/report/base.py
primestg/report/reports.py
primestg-1.55.0.dist-info/LICENSE
primestg-1.55.0.dist-info/METADATA
primestg-1.55.0.dist-info/WHEEL
primestg-1.55.0.dist-info/entry_points.txt
primestg-1.55.0.dist-info/top_level.txt
primestg-1.55.0.dist-info/RECORD
