Metadata-Version: 2.2
Name: primestg
Version: 1.55.0
Summary: Prime STG-DC Interface Specification
Home-page: https://github.com/gisce/primestg
Author: GISCE-TI, S.L.
Author-email: devel@gisce.net
License: GNU Affero General Public License v3
Classifier: Development Status :: 5 - Production/Stable
Classifier: Intended Audience :: Developers
Classifier: License :: OSI Approved :: GNU Affero General Public License v3
Classifier: Operating System :: OS Independent
Classifier: Programming Language :: Python
Classifier: Programming Language :: Python :: 2
Classifier: Programming Language :: Python :: 2.7
Classifier: Programming Language :: Python :: 3
Classifier: Programming Language :: Python :: 3.6
License-File: LICENSE
Requires-Dist: lxml
Requires-Dist: zeep<4.0
Requires-Dist: libcomxml
Requires-Dist: python-dateutil
Dynamic: author
Dynamic: author-email
Dynamic: classifier
Dynamic: description
Dynamic: home-page
Dynamic: license
Dynamic: requires-dist
Dynamic: summary
